scb_profile_x/Prompt-Light.ttf
scb_profile_x/Prompt-Medium.ttf
scb_profile_x/Prompt-Regular.ttf
scb_profile_x/Prompt-SemiBold.ttf
scb_profile_x/__init__.py
scb_profile_x/data_preparation.py
scb_profile_x/profile_x_template_v3_18_rows.png
scb_profile_x/profile_x_template_v3_18_rows_single_target.png
scb_profile_x/profile_x_template_v3_27_rows.png
scb_profile_x/profile_x_template_v3_27_rows_single_target.png
scb_profile_x/version.py
scb_profile_x/visualization.py
scb_profile_x-0.0.9.dist-info/METADATA
scb_profile_x-0.0.9.dist-info/WHEEL
scb_profile_x-0.0.9.dist-info/top_level.txt
scb_profile_x-0.0.9.dist-info/RECORD
