Metadata-Version: 2.1
Name: scb-profile-x
Version: 0.0.9
Summary: Module to generate profile X visualization using CSV or Pandas dataframe
Home-page: https://github.com/snn2spade/scb_profile_x_package
Author: Napat Paopongpaibul
Author-email: napat.paopongpaibul@gmail.com
License: UNKNOWN
Project-URL: Bug Tracker, https://github.com/pypa/sampleproject/issues
Platform: UNKNOWN
Classifier: Programming Language :: Python :: 3
Classifier: License :: OSI Approved :: MIT License
Classifier: Operating System :: OS Independent
Requires-Python: >=3.6
Requires-Dist: Pillow (>=8.1.2)
Requires-Dist: matplotlib (>=3.1.3)
Requires-Dist: ipython (>=7.12.0)
Requires-Dist: pandas (>=1.0.2)
